ibahd_api/__init__.py
ibahd_api/ibahd_api_pb2.py
ibahd_api/ibahd_api_pb2_grpc.py
ibahd_api/utils.py
ibahd_api-1.1.2.dist-info/licenses/LICENSE-MIT.txt
ibahd_api-1.1.2.dist-info/licenses/LICENSE-PROPRIETARY.txt
ibahd_api-1.1.2.dist-info/METADATA
ibahd_api-1.1.2.dist-info/WHEEL
ibahd_api-1.1.2.dist-info/top_level.txt
ibahd_api-1.1.2.dist-info/RECORD
