Metadata-Version: 2.4
Name: ibahd-api
Version: 1.1.2
Summary: Package for handling Python calls to ibaHD-Servers using the ibaHD-API
Author: iba AG
Project-URL: Homepage, https://www.iba-ag.com/
Project-URL: Documentation, https://github.com/iba-ag/ibaHD-API-Sample-Clients/tree/master/python/README.md
Project-URL: Tutorial, https://github.com/iba-ag/ibaHD-API-Sample-Clients/tree/master/python/tutorial.ipynb
Project-URL: License Details, https://www.iba-ag.com/de/license-agreement
Project-URL: Changelog, https://github.com/iba-ag/ibaHD-API-Sample-Clients/tree/master/python/CHANGELOG.md
Keywords: iba_ag,ibahd_server,ibahd_api,api,grpc,protobuf
Classifier: Development Status :: 5 - Production/Stable
Classifier: Intended Audience :: Customer Service
Classifier: Intended Audience :: Developers
Classifier: Intended Audience :: End Users/Desktop
Classifier: Intended Audience :: Manufacturing
Classifier: Intended Audience :: Science/Research
Classifier: Programming Language :: Python :: 3 :: Only
Classifier: Programming Language :: Python :: 3.9
Classifier: Programming Language :: Python :: 3.10
Classifier: Programming Language :: Python :: 3.11
Classifier: Programming Language :: Python :: 3.12
Requires-Python: <3.13,>=3.9
License-File: LICENSE-PROPRIETARY.txt
License-File: LICENSE-MIT.txt
Requires-Dist: grpcio<=1.73.1,>=1.72.1
Requires-Dist: grpcio-tools<=1.73.1,>=1.72.1
Requires-Dist: protobuf<=6.31.1,>=6.30.0
Provides-Extra: tutorial
Requires-Dist: ipykernel<=6.29.5,>=6.14.0; extra == "tutorial"
Requires-Dist: matplotlib<=3.9.4,>=3.7.3; extra == "tutorial"
Requires-Dist: numpy<2.0,>=1.26.4; extra == "tutorial"
Requires-Dist: tabulate<=0.9.0,>=0.4.2; extra == "tutorial"
Provides-Extra: dev
Requires-Dist: ipykernel<=6.29.5,>=6.14.0; extra == "dev"
Dynamic: license-file
